alshain/__init__.py
alshain/alshain.py
alshain-0.1.1.dist-info/licenses/LICENSE
alshain-0.1.1.dist-info/METADATA
alshain-0.1.1.dist-info/WHEEL
alshain-0.1.1.dist-info/top_level.txt
alshain-0.1.1.dist-info/RECORD
