Metadata-Version: 2.4
Name: alshain
Version: 0.1.1
Summary: Interface library for Alshain Oy devices
Author-email: Markus Grönholm <markus@alshain.fi>
License-Expression: MIT
Project-URL: Homepage, https://github.com/Alshain-Oy/pyalshain
Project-URL: Issues, https://github.com/Alshain-Oy/pyalshain/issues
Classifier: Programming Language :: Python :: 3
Classifier: Operating System :: OS Independent
Requires-Python: >=3.11
License-File: LICENSE
Dynamic: license-file
